jokeapi/__init__.py
jokeapi/main.py
jokeapi-1.0.4.dist-info/LICENSE.txt
jokeapi-1.0.4.dist-info/WHEEL
jokeapi-1.0.4.dist-info/METADATA
jokeapi-1.0.4.dist-info/RECORD
