Metadata-Version: 2.1
Name: jokeapi
Version: 1.0.4
Summary: Python API Wrapper for Sv443's JokeAPI (https://v2.jokeapi.dev)
Home-page: https://pypi.org/project/jokeapi
License: GPL-3.0-only
Author: leet-hakker
Author-email: thenamesweretakenalready@gmail.com
Maintainer: leet-hakker
Requires-Python: >=3.7,<4.0
Classifier: License :: OSI Approved :: GNU General Public License v3 (GPLv3)
Classifier: Programming Language :: Python :: 3
Classifier: Programming Language :: Python :: 3.10
Classifier: Programming Language :: Python :: 3.7
Classifier: Programming Language :: Python :: 3.8
Classifier: Programming Language :: Python :: 3.9
Requires-Dist: aiohttp (>=3.7.4,<4.0.0)
Requires-Dist: simplejson (>=3.17.2,<4.0.0)
Requires-Dist: urllib3 (>=1.26.2,<2.0.0)
Project-URL: Repository, https://github.com/leet-hakker/JokeAPI-Python
